mysdq
