Metadata-Version: 1.1
Name: mysdq
Version: 0.3
Summary: Simple Django queryset like dict querer
Home-page: https://github.com/josuebrunel/mysdq/
Author: Josue Kouka
Author-email: josuebrunel@gmail.com
License: MIT
Download-URL: https://github.com/josuebrunel/mysdq/archive/0.3.tar.gz
Keywords: dictquery,queryset,dict,query
Platform: Any
Classifier: Programming Language :: Python
Classifier: Programming Language :: Python :: 2
Classifier: Programming Language :: Python :: 3
Classifier: Development Status :: 5 - Production/Stable
Classifier: Topic :: Software Development :: Libraries :: Python Modules
Classifier: Environment :: Console
Classifier: Intended Audience :: Developers
Classifier: License :: OSI Approved :: MIT License
